zap_installer/__init__.py
zap_installer/zap.py
zap_installer-0.1.1.dist-info/METADATA
zap_installer-0.1.1.dist-info/WHEEL
zap_installer-0.1.1.dist-info/entry_points.txt
zap_installer-0.1.1.dist-info/top_level.txt
zap_installer-0.1.1.dist-info/RECORD
