Metadata-Version: 2.1
Name: zap-installer
Version: 0.1.1
Summary: A script to download and install OWASP ZAP
Author: Udit
Author-email: uditrajsingh815@example.com
Classifier: Programming Language :: Python :: 3
Classifier: License :: OSI Approved :: MIT License
Classifier: Operating System :: OS Independent
Requires-Python: >=3.6
Requires-Dist: requests >=2.25.1
